pytest_docker_db/__init__.py
pytest_docker_db/plugin.py
pytest_docker_db/util.py
pytest_docker_db-1.1.0.dist-info/LICENSE
pytest_docker_db-1.1.0.dist-info/METADATA
pytest_docker_db-1.1.0.dist-info/WHEEL
pytest_docker_db-1.1.0.dist-info/entry_points.txt
pytest_docker_db-1.1.0.dist-info/top_level.txt
pytest_docker_db-1.1.0.dist-info/RECORD
