Metadata-Version: 2.1
Name: pytest-docker-db
Version: 1.1.0
Summary: A plugin to use docker databases for pytests
Home-page: https://github.com/kprestel/pytest-docker-db
Author: Kyle Prestel
Author-email: kprestel@gmail.com
Maintainer: Kyle Prestel
Maintainer-email: kprestel@gmail.com
License: MIT
Keywords: pytest docker database py.test postgres mysql sqlserver MSSQL
Platform: UNKNOWN
Classifier: Development Status :: 5 - Production/Stable
Classifier: Framework :: Pytest
Classifier: Intended Audience :: Developers
Classifier: Topic :: Software Development :: Testing
Classifier: Programming Language :: Python
Classifier: Programming Language :: Python :: 3.7
Classifier: Programming Language :: Python :: 3.8
Classifier: Programming Language :: Python :: 3.9
Classifier: Programming Language :: Python :: Implementation :: CPython
Classifier: Operating System :: OS Independent
Classifier: License :: OSI Approved :: MIT License
Requires-Python: >=3.6
Requires-Dist: pytest (>=3.1.1)
Requires-Dist: docker (>=3.1.0)
